.bumpversion.cfg
.gitignore
MANIFEST.in
Makefile
README.rst
pypackage.mk
requirements.txt
setup.py
.circleci/config.yml
src/SystemCmd_z6.egg-info/PKG-INFO
src/SystemCmd_z6.egg-info/SOURCES.txt
src/SystemCmd_z6.egg-info/dependency_links.txt
src/SystemCmd_z6.egg-info/entry_points.txt
src/SystemCmd_z6.egg-info/requires.txt
src/SystemCmd_z6.egg-info/top_level.txt
src/system_cmd/__init__.py
src/system_cmd/interface.py
src/system_cmd/meat.py
src/system_cmd/structures.py
src/system_cmd/test_one.py
src/system_cmd/utils.py
src/system_cmd/which.py