Metadata-Version: 1.1
Name: SystemCmd-z6
Version: 3.0.5
Summary: My wrappers for subprocess.POpen
Home-page: http://github.com/AndreaCensi/system_cmd
Author: Andrea Censi
Author-email: censi@mit.edu
License: UNKNOWN
Download-URL: http://github.com/AndreaCensi/system_cmd/tarball/3.0.5
Platform: UNKNOWN
Classifier: Development Status :: 4 - Beta
